imio.plausible-1.0a1-py3.10-nspkg.pth
imio/plausible/__init__.py
imio/plausible/configure.zcml
imio/plausible/interfaces.py
imio/plausible/permissions.zcml
imio/plausible/setuphandlers.py
imio/plausible/testing.py
imio/plausible/utils.py
imio/plausible/browser/__init__.py
imio/plausible/browser/configure.zcml
imio/plausible/browser/overrides/.gitkeep
imio/plausible/browser/static/.gitkeep
imio/plausible/controlpanels/__init__.py
imio/plausible/controlpanels/configure.zcml
imio/plausible/controlpanels/plausible_control_panel/__init__.py
imio/plausible/controlpanels/plausible_control_panel/configure.zcml
imio/plausible/controlpanels/plausible_control_panel/controlpanel.py
imio/plausible/locales/README.rst
imio/plausible/locales/__init__.py
imio/plausible/locales/imio.plausible.pot
imio/plausible/locales/update.py
imio/plausible/locales/update.sh
imio/plausible/locales/en/LC_MESSAGES/imio.plausible.po
imio/plausible/locales/fr/LC_MESSAGES/imio.plausible.po
imio/plausible/profiles/default/browserlayer.xml
imio/plausible/profiles/default/catalog.xml
imio/plausible/profiles/default/controlpanel.xml
imio/plausible/profiles/default/metadata.xml
imio/plausible/profiles/default/rolemap.xml
imio/plausible/profiles/default/registry/main.xml
imio/plausible/profiles/default/registry/plausible_control_panel.xml
imio/plausible/profiles/uninstall/browserlayer.xml
imio/plausible/tests/__init__.py
imio/plausible/tests/test_robot.py
imio/plausible/tests/test_setup.py
imio/plausible/tests/test_view_plausible_view.py
imio/plausible/tests/robot/test_example.robot
imio/plausible/views/__init__.py
imio/plausible/views/configure.zcml
imio/plausible/views/plausible_view.pt
imio/plausible/views/plausible_view.py
imio.plausible-1.0a1.dist-info/LICENSE.GPL
imio.plausible-1.0a1.dist-info/LICENSE.rst
imio.plausible-1.0a1.dist-info/METADATA
imio.plausible-1.0a1.dist-info/WHEEL
imio.plausible-1.0a1.dist-info/entry_points.txt
imio.plausible-1.0a1.dist-info/namespace_packages.txt
imio.plausible-1.0a1.dist-info/top_level.txt
imio.plausible-1.0a1.dist-info/RECORD
