Metadata-Version: 2.1
Name: imio.plausible
Version: 1.0a1
Summary: Plausible integration into Plone 5 and Plone 6 classic UI
Home-page: https://github.com/IMIO/imio.plausible
Author: remdub
Author-email: remi.dubois@imio.be
License: GPL version 2
Project-URL: PyPI, https://pypi.org/project/imio.plausible/
Project-URL: Source, https://github.com/IMIO/imio.plausible
Project-URL: Tracker, https://github.com/IMIO/imio.plausible/issues
Keywords: Python Plone CMS
Classifier: Environment :: Web Environment
Classifier: Framework :: Plone
Classifier: Framework :: Plone :: Addon
Classifier: Framework :: Plone :: 5.2
Classifier: Framework :: Plone :: 6.0
Classifier: Programming Language :: Python
Classifier: Programming Language :: Python :: 3.7
Classifier: Programming Language :: Python :: 3.8
Classifier: Programming Language :: Python :: 3.9
Classifier: Operating System :: OS Independent
Classifier: License :: OSI Approved :: GNU General Public License v2 (GPLv2)
Requires-Python: >=3.7
License-File: LICENSE.GPL
License-File: LICENSE.rst
Requires-Dist: setuptools
Requires-Dist: z3c.jbot
Requires-Dist: plone.api >=1.8.4
Requires-Dist: plone.app.dexterity
Provides-Extra: test
Requires-Dist: plone.app.testing ; extra == 'test'
Requires-Dist: plone.testing >=5.0.0 ; extra == 'test'
Requires-Dist: plone.app.contenttypes ; extra == 'test'
Requires-Dist: plone.app.robotframework[debug] ; extra == 'test'
